chemfileconverter/__init__.py
chemfileconverter/__main__.py
chemfileconverter/cli.py
chemfileconverter-0.1.0.dist-info/AUTHORS.rst
chemfileconverter-0.1.0.dist-info/LICENSE
chemfileconverter-0.1.0.dist-info/METADATA
chemfileconverter-0.1.0.dist-info/WHEEL
chemfileconverter-0.1.0.dist-info/entry_points.txt
chemfileconverter-0.1.0.dist-info/top_level.txt
chemfileconverter-0.1.0.dist-info/RECORD
