Metadata-Version: 2.1
Name: chemfileconverter
Version: 0.1.0
Summary: A python converter for Chemical Table Files.
Home-page: https://github.com/CollinStark/chemfileconverter
Author: Collin Starke
Author-email: c.starke@tu-bs.de
License: BSD-2-Clause
Project-URL: Documentation, https://chemfileconverter.readthedocs.io/
Project-URL: Changelog, https://chemfileconverter.readthedocs.io/en/latest/changelog.html
Project-URL: Issue Tracker, https://github.com/CollinStark/chemfileconverter/issues
Platform: UNKNOWN
Classifier: Development Status :: 5 - Production/Stable
Classifier: Intended Audience :: Developers
Classifier: License :: OSI Approved :: BSD License
Classifier: Operating System :: Unix
Classifier: Operating System :: POSIX
Classifier: Operating System :: Microsoft :: Windows
Classifier: Programming Language :: Python
Classifier: Programming Language :: Python :: 3
Classifier: Programming Language :: Python :: 3 :: Only
Classifier: Programming Language :: Python :: 3.10
Classifier: Programming Language :: Python :: Implementation :: CPython
Classifier: Programming Language :: Python :: Implementation :: PyPy
Classifier: Topic :: Utilities
Requires-Python: >=3.10
License-File: LICENSE
License-File: AUTHORS.rst
Requires-Dist: json
